{
  "name": "Late Buyers After Movement",
  "description": "Small trades early, then larger buys after the price has already moved significantly. Useful for observing how b affects late-stage price sensitivity.",
  "trades": [
    {"user": "alice",   "yes": 2, "no": 0},
    {"user": "bob",     "yes": 0, "no": 3},
    {"user": "charlie", "yes": 1, "no": 0},
    {"user": "diana",   "yes": 0, "no": 2},
    {"user": "eve",     "yes": 2, "no": 0},
    {"user": "frank",   "yes": 0, "no": 1},
    {"user": "alice",   "yes": 1, "no": 0},
    {"user": "bob",     "yes": 0, "no": 2},
    {"user": "charlie", "yes": 3, "no": 0},
    {"user": "diana",   "yes": 0, "no": 1},
    {"user": "eve",     "yes": 15, "no": 0},
    {"user": "frank",   "yes": 0,  "no": 10},
    {"user": "alice",   "yes": 4,  "no": 0},
    {"user": "bob",     "yes": 0,  "no": 3},
    {"user": "charlie", "yes": 2,  "no": 0},
    {"user": "diana",   "yes": 0,  "no": 5},
    {"user": "eve",     "yes": 3,  "no": 0},
    {"user": "frank",   "yes": 0,  "no": 2},
    {"user": "alice",   "yes": 5,  "no": 0},
    {"user": "bob",     "yes": 0,  "no": 4},
    {"user": "charlie", "yes": 2,  "no": 0},
    {"user": "diana",   "yes": 0,  "no": 3}
  ]
}